sqliteasy/__init__.py
sqliteasy/modules.py
sqliteasy-0.2.0.dist-info/METADATA
sqliteasy-0.2.0.dist-info/WHEEL
sqliteasy-0.2.0.dist-info/top_level.txt
sqliteasy-0.2.0.dist-info/RECORD
