Metadata-Version: 2.2
Name: sqliteasy
Version: 0.2.0
Summary: An easy SQLite wrapper for Python.
Author: Josué Arias Gauna
Author-email: josuearias.crc@gmail.com
Requires-Python: >=3.6
Dynamic: author
Dynamic: author-email
Dynamic: description
Dynamic: description-content-type
Dynamic: requires-python
Dynamic: summary
